django_numerators/__init__.py
django_numerators/admin.py
django_numerators/apps.py
django_numerators/models.py
django_numerators/migrations/0001_initial.py
django_numerators/migrations/0002_auto_20200410_0236.py
django_numerators/migrations/__init__.py
django_numerators/utils/__init__.py
django_numerators/utils/version.py
django_numerators-0.0.2.dist-info/LICENSE
django_numerators-0.0.2.dist-info/METADATA
django_numerators-0.0.2.dist-info/WHEEL
django_numerators-0.0.2.dist-info/top_level.txt
django_numerators-0.0.2.dist-info/RECORD
