Metadata-Version: 2.1
Name: django-numerators
Version: 0.0.2
Summary: Django simple numerator, tests included
Home-page: https://github.com/sasriawesome/django_numerators
Maintainer: Rizki Sasri Dwitama
Maintainer-email: sasri.project@gmail.com
License: MIT
Platform: UNKNOWN
Classifier: Development Status :: 3 - Alpha
Classifier: Environment :: Web Environment
Classifier: Framework :: Django
Classifier: Intended Audience :: Developers
Classifier: License :: OSI Approved :: BSD License
Classifier: Operating System :: OS Independent
Classifier: Programming Language :: Python
Classifier: Topic :: Software Development :: Libraries :: Python Modules
Requires-Dist: Django (>=2.2)
